thonnycontrib/pi/__init__.py
thonnycontrib/pi/res/debug-run-cursor.png
thonnycontrib/pi/res/debug-run-cursor48.png
thonnycontrib/pi/res/debug-run.png
thonnycontrib/pi/res/debug-run48.png
thonnycontrib/pi/res/debug-step-into.png
thonnycontrib/pi/res/debug-step-into48.png
thonnycontrib/pi/res/debug-step-out.png
thonnycontrib/pi/res/debug-step-out48.png
thonnycontrib/pi/res/debug-step-over.png
thonnycontrib/pi/res/debug-step-over48.png
thonnycontrib/pi/res/document-new.png
thonnycontrib/pi/res/document-new48.png
thonnycontrib/pi/res/document-open.png
thonnycontrib/pi/res/document-open48.png
thonnycontrib/pi/res/document-save.png
thonnycontrib/pi/res/document-save48.png
thonnycontrib/pi/res/media-playback-start.png
thonnycontrib/pi/res/media-playback-start48.png
thonnycontrib/pi/res/process-stop.png
thonnycontrib/pi/res/process-stop48.png
thonnycontrib/pi/res/quit.png
thonnycontrib/pi/res/quit48.png
thonnycontrib/pi/res/resume.png
thonnycontrib/pi/res/resume48.png
thonnycontrib/pi/res/scrollbar-button-down-insens.png
thonnycontrib/pi/res/scrollbar-button-down.png
thonnycontrib/pi/res/scrollbar-button-left-insens.png
thonnycontrib/pi/res/scrollbar-button-left.png
thonnycontrib/pi/res/scrollbar-button-right-insens.png
thonnycontrib/pi/res/scrollbar-button-right.png
thonnycontrib/pi/res/scrollbar-button-up-insens.png
thonnycontrib/pi/res/scrollbar-button-up.png
thonnycontrib/pi/res/window-close-act.png
thonnycontrib/pi/res/window-close.png
thonnycontrib/pi/res/zoom.png
thonnycontrib/pi/res/zoom48.png
thonny_pi-1.5.dist-info/LICENSE.txt
thonny_pi-1.5.dist-info/METADATA
thonny_pi-1.5.dist-info/WHEEL
thonny_pi-1.5.dist-info/top_level.txt
thonny_pi-1.5.dist-info/RECORD
